micropython_ms5611/__init__.py
micropython_ms5611/i2c_helpers.py
micropython_ms5611/ms5611.py
micropython_ms5611-0.1.0.dist-info/LICENSE
micropython_ms5611-0.1.0.dist-info/METADATA
micropython_ms5611-0.1.0.dist-info/WHEEL
micropython_ms5611-0.1.0.dist-info/top_level.txt
micropython_ms5611-0.1.0.dist-info/RECORD
