Metadata-Version: 2.1
Name: micropython-ms5611
Version: 0.1.0
Summary: MicroPython Driver for the TE MS5611 Pressure and Temperature Sensor
Author-email: JDM <xxyx@mailmeto.mozmail.com>
License: MIT
Project-URL: Homepage, https://github.com/jposada202020/MicroPython_MS5611
Keywords: sensor,micropython,ms5611,micropython,temperature,sensor,driver,pressure,ms5611
Classifier: Intended Audience :: Developers
Classifier: Topic :: Software Development :: Libraries
Classifier: Topic :: Software Development :: Embedded Systems
Classifier: Topic :: System :: Hardware
Classifier: License :: OSI Approved :: MIT License
Classifier: Programming Language :: Python :: Implementation :: MicroPython
License-File: LICENSE
